wlogging/__init__.py
wlogging/formatters.py
wlogging/loggers.py
wlogging-0.4.0.dist-info/METADATA
wlogging-0.4.0.dist-info/WHEEL
wlogging-0.4.0.dist-info/RECORD
