Metadata-Version: 2.3
Name: wlogging
Version: 0.4.0
Summary: Pythonic wrapper for the standard logging module
Project-URL: Homepage, https://github.com/iris-solutions-team/wlogging
Project-URL: Bug Tracker, https://github.com/iris-solutions-team/wlogging/issues
Author-email: Jaromir Benes <jaromir.benes@gmail.com>
Keywords: logging
Classifier: License :: OSI Approved :: MIT License
Classifier: Operating System :: OS Independent
Classifier: Programming Language :: Python :: 3
Requires-Python: >=3.11
